<?xml version="1.0" encoding="utf-8"?><soap:Envelope xmlns:soap="http://schemas.xmlsoap.org/soap/envelope/" xmlns:xsi="http://www.w3.org/2001/XMLSchema-instance" xmlns:xsd="http://www.w3.org/2001/XMLSchema"><soap:Body><GetListItemsResponse xmlns="http://schemas.microsoft.com/sharepoint/soap/"><GetListItemsResult><listitems xmlns:s='uuid:BDC6E3F0-6DA3-11d1-A2A3-00AA00C14882'
     xmlns:dt='uuid:C2F41010-65B3-11d1-A29F-00AA00C14882'
     xmlns:rs='urn:schemas-microsoft-com:rowset'
     xmlns:z='#RowsetSchema'>
<rs:data ItemCount="88">
   <z:row ows_ID='1' ows_Attachments='0' ows_Campaign_id='3' ows_Stage='to-pipeline' ows_Score='0' ows_Override='1' ows_StartDate='2013-12-13 00:00:00' ows_Roi='0.00' ows_RoiPass='0' ows_HasPreanalysis='0' ows_Nicpl='0.00' ows_NicplPass='0' ows_Nic='0' ows__ModerationStatus='0' ows__Level='1' ows_UniqueId='1;#{8C9854A4-A6FF-4E42-AE4C-4EEA31EA7520}' ows_FSObjType='1;#0' ows_Created_x0020_Date='1;#2013-12-20 09:26:07' ows_FileLeafRef='1;#1_.000' ows_FileRef='1;#sites/rbs/DDM/Lists/prodoutcomecampaign/1_.000' ows_MetaInfo='1;#' ows_owshiddenversion='1' ows_Created='2013-12-20 09:26:07' />
   <z:row ows_ID='2' ows_Attachments='0' ows_Campaign_id='11' ows_Stage='to-pipeline' ows_Score='0' ows_Override='0' ows_StartDate='2014-01-01 00:00:00' ows_Roi='0.00' ows_RoiPass='0' ows_HasPreanalysis='0' ows_Nicpl='0.00' ows_NicplPass='0' ows_Nic='0' ows__ModerationStatus='0' ows__Level='1' ows_UniqueId='2;#{2F6DE9B3-8CD9-4291-9DC1-81B2D493BF31}' ows_FSObjType='2;#0' ows_Created_x0020_Date='2;#2013-12-20 09:26:07' ows_FileLeafRef='2;#2_.000' ows_FileRef='2;#sites/rbs/DDM/Lists/prodoutcomecampaign/2_.000' ows_MetaInfo='2;#' ows_owshiddenversion='1' ows_Created='2013-12-20 09:26:07' />
   <z:row ows_ID='3' ows_Attachments='0' ows_Campaign_id='4' ows_Stage='to-pipeline' ows_Score='0' ows_Override='0' ows_StartDate='2014-01-10 00:00:00' ows_Roi='0.00' ows_RoiPass='0' ows_HasPreanalysis='0' ows_Nicpl='0.00' ows_NicplPass='0' ows_Nic='0' ows__ModerationStatus='0' ows__Level='1' ows_UniqueId='3;#{04EF44DA-B480-4A97-9986-37ACE3F5D582}' ows_FSObjType='3;#0' ows_Created_x0020_Date='3;#2013-12-20 09:26:07' ows_FileLeafRef='3;#3_.000' ows_FileRef='3;#sites/rbs/DDM/Lists/prodoutcomecampaign/3_.000' ows_MetaInfo='3;#' ows_owshiddenversion='1' ows_Created='2013-12-20 09:26:07' />
   <z:row ows_ID='4' ows_Attachments='0' ows_Campaign_id='6' ows_Stage='priority' ows_Score='610' ows_Override='0' ows_StartDate='2013-12-30 00:00:00' ows_Roi='38.00' ows_RoiPass='1' ows_HasPreanalysis='1' ows_Nicpl='19.00' ows_NicplPass='1' ows_Nic='6,080,000' ows__ModerationStatus='0' ows__Level='1' ows_UniqueId='4;#{FB849D44-1074-41EE-8F3F-8FC1183F6725}' ows_FSObjType='4;#0' ows_Created_x0020_Date='4;#2013-12-20 09:26:07' ows_FileLeafRef='4;#4_.000' ows_FileRef='4;#sites/rbs/DDM/Lists/prodoutcomecampaign/4_.000' ows_MetaInfo='4;#' ows_owshiddenversion='1' ows_Created='2013-12-20 09:26:07' />
   <z:row ows_ID='5' ows_Attachments='0' ows_Campaign_id='5' ows_Stage='priority' ows_Score='540' ows_Override='0' ows_StartDate='2014-02-03 00:00:00' ows_Roi='893.90' ows_RoiPass='1' ows_HasPreanalysis='1' ows_Nicpl='8.94' ows_NicplPass='1' ows_Nic='89,390' ows__ModerationStatus='0' ows__Level='1' ows_UniqueId='5;#{EA97CD6C-7382-4E41-9E6E-E5B18C2A9FF0}' ows_FSObjType='5;#0' ows_Created_x0020_Date='5;#2013-12-20 09:26:07' ows_FileLeafRef='5;#5_.000' ows_FileRef='5;#sites/rbs/DDM/Lists/prodoutcomecampaign/5_.000' ows_MetaInfo='5;#' ows_owshiddenversion='1' ows_Created='2013-12-20 09:26:07' />
   <z:row ows_ID='6' ows_Attachments='0' ows_Campaign_id='8' ows_Stage='priority' ows_Score='0' ows_Override='0' ows_StartDate='2014-01-13 00:00:00' ows_Roi='1.40' ows_RoiPass='0' ows_HasPreanalysis='1' ows_Nicpl='9.81' ows_NicplPass='1' ows_Nic='127,530' ows__ModerationStatus='0' ows__Level='1' ows_UniqueId='6;#{B226091E-A70F-45F5-92D4-B706680199D0}' ows_FSObjType='6;#0' ows_Created_x0020_Date='6;#2013-12-20 09:26:07' ows_FileLeafRef='6;#6_.000' ows_FileRef='6;#sites/rbs/DDM/Lists/prodoutcomecampaign/6_.000' ows_MetaInfo='6;#' ows_owshiddenversion='1' ows_Created='2013-12-20 09:26:07' />
   <z:row ows_ID='7' ows_Attachments='0' ows_Campaign_id='7' ows_Stage='priority' ows_Score='0' ows_Override='0' ows_StartDate='2014-01-10 00:00:00' ows_Roi='10.19' ows_RoiPass='1' ows_HasPreanalysis='1' ows_Nicpl='0.10' ows_NicplPass='0' ows_Nic='22,418' ows__ModerationStatus='0' ows__Level='1' ows_UniqueId='7;#{216EDCCF-396A-4AAC-BEB9-7B1F7B7086DE}' ows_FSObjType='7;#0' ows_Created_x0020_Date='7;#2013-12-20 09:26:07' ows_FileLeafRef='7;#7_.000' ows_FileRef='7;#sites/rbs/DDM/Lists/prodoutcomecampaign/7_.000' ows_MetaInfo='7;#' ows_owshiddenversion='1' ows_Created='2013-12-20 09:26:07' />
   <z:row ows_ID='8' ows_Attachments='0' ows_Campaign_id='6' ows_Stage='to-pipeline' ows_Score='340' ows_Override='0' ows_StartDate='2013-12-30 00:00:00' ows_Roi='38.00' ows_RoiPass='1' ows_HasPreanalysis='1' ows_Nicpl='19.00' ows_NicplPass='1' ows_Nic='6,080,000' ows__ModerationStatus='0' ows__Level='1' ows_UniqueId='8;#{A631205E-6649-4CD3-8366-8465D8572155}' ows_FSObjType='8;#0' ows_Created_x0020_Date='8;#2013-12-20 09:54:53' ows_FileLeafRef='8;#8_.000' ows_FileRef='8;#sites/rbs/DDM/Lists/prodoutcomecampaign/8_.000' ows_MetaInfo='8;#' ows_owshiddenversion='1' ows_Created='2013-12-20 09:54:53' />
   <z:row ows_ID='9' ows_Attachments='0' ows_Campaign_id='5' ows_Stage='priority' ows_Score='270' ows_Override='0' ows_StartDate='2014-02-03 00:00:00' ows_Roi='893.90' ows_RoiPass='1' ows_HasPreanalysis='1' ows_Nicpl='8.94' ows_NicplPass='1' ows_Nic='89,390' ows__ModerationStatus='0' ows__Level='1' ows_UniqueId='9;#{4EA37AA3-8061-497C-9C69-C2B78ABB5AC7}' ows_FSObjType='9;#0' ows_Created_x0020_Date='9;#2013-12-20 09:54:53' ows_FileLeafRef='9;#9_.000' ows_FileRef='9;#sites/rbs/DDM/Lists/prodoutcomecampaign/9_.000' ows_MetaInfo='9;#' ows_owshiddenversion='1' ows_Created='2013-12-20 09:54:53' />
   <z:row ows_ID='10' ows_Attachments='0' ows_Campaign_id='7' ows_Stage='priority' ows_Score='0' ows_Override='0' ows_StartDate='2014-01-10 00:00:00' ows_Roi='10.19' ows_RoiPass='1' ows_HasPreanalysis='1' ows_Nicpl='0.10' ows_NicplPass='0' ows_Nic='22,418' ows__ModerationStatus='0' ows__Level='1' ows_UniqueId='10;#{7914A8A2-4183-44A2-BA35-A3065EF4A623}' ows_FSObjType='10;#0' ows_Created_x0020_Date='10;#2013-12-20 09:54:53' ows_FileLeafRef='10;#10_.000' ows_FileRef='10;#sites/rbs/DDM/Lists/prodoutcomecampaign/10_.000' ows_MetaInfo='10;#' ows_owshiddenversion='1' ows_Created='2013-12-20 09:54:53' />
   <z:row ows_ID='11' ows_Attachments='0' ows_Campaign_id='8' ows_Stage='priority' ows_Score='0' ows_Override='0' ows_StartDate='2014-01-13 00:00:00' ows_Roi='1.40' ows_RoiPass='0' ows_HasPreanalysis='1' ows_Nicpl='9.81' ows_NicplPass='1' ows_Nic='127,530' ows__ModerationStatus='0' ows__Level='1' ows_UniqueId='11;#{473D0D54-018B-4E01-8C7B-FA21B904A5C3}' ows_FSObjType='11;#0' ows_Created_x0020_Date='11;#2013-12-20 09:54:53' ows_FileLeafRef='11;#11_.000' ows_FileRef='11;#sites/rbs/DDM/Lists/prodoutcomecampaign/11_.000' ows_MetaInfo='11;#' ows_owshiddenversion='1' ows_Created='2013-12-20 09:54:53' />
   <z:row ows_ID='12' ows_Attachments='0' ows_Campaign_id='5' ows_Stage='to-pipeline' ows_Score='230' ows_Override='0' ows_StartDate='2014-02-03 00:00:00' ows_Roi='893.90' ows_RoiPass='1' ows_HasPreanalysis='1' ows_Nicpl='8.94' ows_NicplPass='1' ows_Nic='89,390' ows__ModerationStatus='0' ows__Level='1' ows_UniqueId='12;#{51EE1704-C1FE-48BF-864A-424C0A25615D}' ows_FSObjType='12;#0' ows_Created_x0020_Date='12;#2013-12-20 09:57:18' ows_FileLeafRef='12;#12_.000' ows_FileRef='12;#sites/rbs/DDM/Lists/prodoutcomecampaign/12_.000' ows_MetaInfo='12;#' ows_owshiddenversion='1' ows_Created='2013-12-20 09:57:18' />
   <z:row ows_ID='13' ows_Attachments='0' ows_Campaign_id='7' ows_Stage='priority' ows_Score='0' ows_Override='0' ows_StartDate='2014-01-10 00:00:00' ows_Roi='10.19' ows_RoiPass='1' ows_HasPreanalysis='1' ows_Nicpl='0.10' ows_NicplPass='0' ows_Nic='22,418' ows__ModerationStatus='0' ows__Level='1' ows_UniqueId='13;#{F4E0C519-3D51-445E-BAEB-F98E777B9A55}' ows_FSObjType='13;#0' ows_Created_x0020_Date='13;#2013-12-20 09:57:18' ows_FileLeafRef='13;#13_.000' ows_FileRef='13;#sites/rbs/DDM/Lists/prodoutcomecampaign/13_.000' ows_MetaInfo='13;#' ows_owshiddenversion='1' ows_Created='2013-12-20 09:57:18' />
   <z:row ows_ID='14' ows_Attachments='0' ows_Campaign_id='8' ows_Stage='priority' ows_Score='0' ows_Override='0' ows_StartDate='2014-01-13 00:00:00' ows_Roi='1.40' ows_RoiPass='0' ows_HasPreanalysis='1' ows_Nicpl='9.81' ows_NicplPass='1' ows_Nic='127,530' ows__ModerationStatus='0' ows__Level='1' ows_UniqueId='14;#{6271FE21-9E96-4C2B-ADE5-05E77C5709F2}' ows_FSObjType='14;#0' ows_Created_x0020_Date='14;#2013-12-20 09:57:18' ows_FileLeafRef='14;#14_.000' ows_FileRef='14;#sites/rbs/DDM/Lists/prodoutcomecampaign/14_.000' ows_MetaInfo='14;#' ows_owshiddenversion='1' ows_Created='2013-12-20 09:57:18' />
   <z:row ows_ID='15' ows_Attachments='0' ows_Campaign_id='7' ows_Stage='to-pipeline' ows_Score='0' ows_Override='0' ows_StartDate='2014-01-10 00:00:00' ows_Roi='10.19' ows_RoiPass='1' ows_HasPreanalysis='1' ows_Nicpl='0.10' ows_NicplPass='0' ows_Nic='22,418' ows__ModerationStatus='0' ows__Level='1' ows_UniqueId='15;#{E0E8A178-6C20-4B86-8815-BC59C7C28290}' ows_FSObjType='15;#0' ows_Created_x0020_Date='15;#2013-12-20 10:01:44' ows_FileLeafRef='15;#15_.000' ows_FileRef='15;#sites/rbs/DDM/Lists/prodoutcomecampaign/15_.000' ows_MetaInfo='15;#' ows_owshiddenversion='1' ows_Created='2013-12-20 10:01:44' />
   <z:row ows_ID='16' ows_Attachments='0' ows_Campaign_id='8' ows_Stage='priority' ows_Score='0' ows_Override='0' ows_StartDate='2014-01-13 00:00:00' ows_Roi='1.40' ows_RoiPass='0' ows_HasPreanalysis='1' ows_Nicpl='9.81' ows_NicplPass='1' ows_Nic='127,530' ows__ModerationStatus='0' ows__Level='1' ows_UniqueId='16;#{97D78874-F86A-455C-AE77-6A75CF0EFA8E}' ows_FSObjType='16;#0' ows_Created_x0020_Date='16;#2013-12-20 10:01:44' ows_FileLeafRef='16;#16_.000' ows_FileRef='16;#sites/rbs/DDM/Lists/prodoutcomecampaign/16_.000' ows_MetaInfo='16;#' ows_owshiddenversion='1' ows_Created='2013-12-20 10:01:44' />
   <z:row ows_ID='17' ows_Attachments='0' ows_Campaign_id='8' ows_Stage='to-pipeline' ows_Score='0' ows_Override='0' ows_StartDate='2014-01-13 00:00:00' ows_Roi='1.40' ows_RoiPass='0' ows_HasPreanalysis='1' ows_Nicpl='9.81' ows_NicplPass='1' ows_Nic='127,530' ows__ModerationStatus='0' ows__Level='1' ows_UniqueId='17;#{73B96A4E-94AC-4018-A34A-E09212EEF866}' ows_FSObjType='17;#0' ows_Created_x0020_Date='17;#2013-12-20 10:08:43' ows_FileLeafRef='17;#17_.000' ows_FileRef='17;#sites/rbs/DDM/Lists/prodoutcomecampaign/17_.000' ows_MetaInfo='17;#' ows_owshiddenversion='1' ows_Created='2013-12-20 10:08:43' />
   <z:row ows_ID='18' ows_Attachments='0' ows_Campaign_id='17' ows_Stage='to-pipeline' ows_Score='0' ows_Override='1' ows_StartDate='2014-01-08 00:00:00' ows_Roi='0.00' ows_RoiPass='0' ows_HasPreanalysis='0' ows_Nicpl='0.00' ows_NicplPass='0' ows_Nic='0' ows__ModerationStatus='0' ows__Level='1' ows_UniqueId='18;#{B1AEC11A-1D93-4AFB-BC30-1DD3E54219F8}' ows_FSObjType='18;#0' ows_Created_x0020_Date='18;#2014-01-10 10:55:40' ows_FileLeafRef='18;#18_.000' ows_FileRef='18;#sites/rbs/DDM/Lists/prodoutcomecampaign/18_.000' ows_MetaInfo='18;#' ows_owshiddenversion='1' ows_Created='2014-01-10 10:55:40' />
   <z:row ows_ID='19' ows_Attachments='0' ows_Campaign_id='9' ows_Stage='priority' ows_Score='0' ows_Override='0' ows_StartDate='2014-02-05 00:00:00' ows_Roi='82.54' ows_RoiPass='1' ows_HasPreanalysis='1' ows_Nicpl='0.49' ows_NicplPass='0' ows_Nic='652,100' ows__ModerationStatus='0' ows__Level='1' ows_UniqueId='19;#{5C9E3A87-E95B-45D7-ADA2-FF53408840BC}' ows_FSObjType='19;#0' ows_Created_x0020_Date='19;#2014-01-10 10:55:40' ows_FileLeafRef='19;#19_.000' ows_FileRef='19;#sites/rbs/DDM/Lists/prodoutcomecampaign/19_.000' ows_MetaInfo='19;#' ows_owshiddenversion='1' ows_Created='2014-01-10 10:55:40' />
   <z:row ows_ID='20' ows_Attachments='0' ows_Campaign_id='19' ows_Stage='priority' ows_Score='0' ows_Override='0' ows_StartDate='2014-01-29 00:00:00' ows_Roi='0.55' ows_RoiPass='0' ows_HasPreanalysis='1' ows_Nicpl='9.59' ows_NicplPass='1' ows_Nic='28,767' ows__ModerationStatus='0' ows__Level='1' ows_UniqueId='20;#{1E7445A9-61CC-40F4-8FEA-15EA14A79723}' ows_FSObjType='20;#0' ows_Created_x0020_Date='20;#2014-01-10 10:55:40' ows_FileLeafRef='20;#20_.000' ows_FileRef='20;#sites/rbs/DDM/Lists/prodoutcomecampaign/20_.000' ows_MetaInfo='20;#' ows_owshiddenversion='1' ows_Created='2014-01-10 10:55:40' />
   <z:row ows_ID='21' ows_Attachments='0' ows_Campaign_id='13' ows_Stage='priority' ows_Score='0' ows_Override='0' ows_StartDate='2014-01-20 00:00:00' ows_Roi='36.24' ows_RoiPass='1' ows_HasPreanalysis='1' ows_Nicpl='1.09' ows_NicplPass='0' ows_Nic='652,320' ows__ModerationStatus='0' ows__Level='1' ows_UniqueId='21;#{A0276F5A-DFEA-418E-9287-A7BAD2AA09D3}' ows_FSObjType='21;#0' ows_Created_x0020_Date='21;#2014-01-10 10:55:40' ows_FileLeafRef='21;#21_.000' ows_FileRef='21;#sites/rbs/DDM/Lists/prodoutcomecampaign/21_.000' ows_MetaInfo='21;#' ows_owshiddenversion='1' ows_Created='2014-01-10 10:55:40' />
   <z:row ows_ID='22' ows_Attachments='0' ows_Campaign_id='15' ows_Stage='priority' ows_Score='0' ows_Override='0' ows_StartDate='2014-01-15 00:00:00' ows_Roi='1.27' ows_RoiPass='0' ows_HasPreanalysis='1' ows_Nicpl='1.00' ows_NicplPass='0' ows_Nic='4,841' ows__ModerationStatus='0' ows__Level='1' ows_UniqueId='22;#{54059446-643F-462C-A871-63FC596BEC5E}' ows_FSObjType='22;#0' ows_Created_x0020_Date='22;#2014-01-10 10:55:40' ows_FileLeafRef='22;#22_.000' ows_FileRef='22;#sites/rbs/DDM/Lists/prodoutcomecampaign/22_.000' ows_MetaInfo='22;#' ows_owshiddenversion='1' ows_Created='2014-01-10 10:55:40' />
   <z:row ows_ID='23' ows_Attachments='0' ows_Campaign_id='18' ows_Stage='priority' ows_Score='0' ows_Override='0' ows_StartDate='2014-03-01 00:00:00' ows_Roi='0.00' ows_RoiPass='0' ows_HasPreanalysis='1' ows_Nicpl='0.00' ows_NicplPass='0' ows_Nic='0' ows__ModerationStatus='0' ows__Level='1' ows_UniqueId='23;#{019B25B5-D186-4528-A60F-CCA0C990359D}' ows_FSObjType='23;#0' ows_Created_x0020_Date='23;#2014-01-10 10:55:40' ows_FileLeafRef='23;#23_.000' ows_FileRef='23;#sites/rbs/DDM/Lists/prodoutcomecampaign/23_.000' ows_MetaInfo='23;#' ows_owshiddenversion='1' ows_Created='2014-01-10 10:55:40' />
   <z:row ows_ID='24' ows_Attachments='0' ows_Campaign_id='9' ows_Stage='to-pipeline' ows_Score='0' ows_Override='0' ows_StartDate='2014-02-05 00:00:00' ows_Roi='61.66' ows_RoiPass='1' ows_HasPreanalysis='1' ows_Nicpl='0.37' ows_NicplPass='0' ows_Nic='487,100' ows__ModerationStatus='0' ows__Level='1' ows_UniqueId='24;#{6A8B7A9A-F92F-46F8-8A84-FAFCCDA86BE3}' ows_FSObjType='24;#0' ows_Created_x0020_Date='24;#2014-01-10 11:14:42' ows_FileLeafRef='24;#24_.000' ows_FileRef='24;#sites/rbs/DDM/Lists/prodoutcomecampaign/24_.000' ows_MetaInfo='24;#' ows_owshiddenversion='1' ows_Created='2014-01-10 11:14:42' />
   <z:row ows_ID='25' ows_Attachments='0' ows_Campaign_id='15' ows_Stage='priority' ows_Score='0' ows_Override='0' ows_StartDate='2014-01-15 00:00:00' ows_Roi='1.27' ows_RoiPass='0' ows_HasPreanalysis='1' ows_Nicpl='1.00' ows_NicplPass='0' ows_Nic='4,841' ows__ModerationStatus='0' ows__Level='1' ows_UniqueId='25;#{78834AFB-6B7F-4A4B-95D7-CC8AC90EA162}' ows_FSObjType='25;#0' ows_Created_x0020_Date='25;#2014-01-10 11:14:42' ows_FileLeafRef='25;#25_.000' ows_FileRef='25;#sites/rbs/DDM/Lists/prodoutcomecampaign/25_.000' ows_MetaInfo='25;#' ows_owshiddenversion='1' ows_Created='2014-01-10 11:14:42' />
   <z:row ows_ID='26' ows_Attachments='0' ows_Campaign_id='13' ows_Stage='priority' ows_Score='0' ows_Override='0' ows_StartDate='2014-01-20 00:00:00' ows_Roi='36.24' ows_RoiPass='1' ows_HasPreanalysis='1' ows_Nicpl='1.09' ows_NicplPass='0' ows_Nic='652,320' ows__ModerationStatus='0' ows__Level='1' ows_UniqueId='26;#{985EC97B-AC80-41FB-BF0F-D64B50A846A7}' ows_FSObjType='26;#0' ows_Created_x0020_Date='26;#2014-01-10 11:14:43' ows_FileLeafRef='26;#26_.000' ows_FileRef='26;#sites/rbs/DDM/Lists/prodoutcomecampaign/26_.000' ows_MetaInfo='26;#' ows_owshiddenversion='1' ows_Created='2014-01-10 11:14:43' />
   <z:row ows_ID='27' ows_Attachments='0' ows_Campaign_id='19' ows_Stage='priority' ows_Score='0' ows_Override='0' ows_StartDate='2014-01-29 00:00:00' ows_Roi='0.55' ows_RoiPass='0' ows_HasPreanalysis='1' ows_Nicpl='9.59' ows_NicplPass='1' ows_Nic='28,767' ows__ModerationStatus='0' ows__Level='1' ows_UniqueId='27;#{DF26F346-FF9F-4880-BCD7-F650618CDA44}' ows_FSObjType='27;#0' ows_Created_x0020_Date='27;#2014-01-10 11:14:43' ows_FileLeafRef='27;#27_.000' ows_FileRef='27;#sites/rbs/DDM/Lists/prodoutcomecampaign/27_.000' ows_MetaInfo='27;#' ows_owshiddenversion='1' ows_Created='2014-01-10 11:14:43' />
   <z:row ows_ID='28' ows_Attachments='0' ows_Campaign_id='19' ows_Stage='to-pipeline' ows_Score='0' ows_Override='0' ows_StartDate='2014-01-29 00:00:00' ows_Roi='2.24' ows_RoiPass='1' ows_HasPreanalysis='1' ows_Nicpl='373.81' ows_NicplPass='1' ows_Nic='56,071' ows__ModerationStatus='0' ows__Level='1' ows_UniqueId='28;#{57D4D6DC-7275-482E-B034-30E5714B77B1}' ows_FSObjType='28;#0' ows_Created_x0020_Date='28;#2014-01-10 13:03:30' ows_FileLeafRef='28;#28_.000' ows_FileRef='28;#sites/rbs/DDM/Lists/prodoutcomecampaign/28_.000' ows_MetaInfo='28;#' ows_owshiddenversion='1' ows_Created='2014-01-10 13:03:30' />
   <z:row ows_ID='29' ows_Attachments='0' ows_Campaign_id='13' ows_Stage='priority' ows_Score='0' ows_Override='0' ows_StartDate='2014-01-20 00:00:00' ows_Roi='36.24' ows_RoiPass='1' ows_HasPreanalysis='1' ows_Nicpl='1.09' ows_NicplPass='0' ows_Nic='652,320' ows__ModerationStatus='0' ows__Level='1' ows_UniqueId='29;#{543327D7-C983-436F-B0F8-866742D13479}' ows_FSObjType='29;#0' ows_Created_x0020_Date='29;#2014-01-10 13:03:30' ows_FileLeafRef='29;#29_.000' ows_FileRef='29;#sites/rbs/DDM/Lists/prodoutcomecampaign/29_.000' ows_MetaInfo='29;#' ows_owshiddenversion='1' ows_Created='2014-01-10 13:03:30' />
   <z:row ows_ID='30' ows_Attachments='0' ows_Campaign_id='13' ows_Stage='to-pipeline' ows_Score='0' ows_Override='0' ows_StartDate='2014-01-20 00:00:00' ows_Roi='36.24' ows_RoiPass='1' ows_HasPreanalysis='1' ows_Nicpl='1.09' ows_NicplPass='0' ows_Nic='652,320' ows__ModerationStatus='0' ows__Level='1' ows_UniqueId='30;#{B7EE48BF-FD5C-491C-905D-AE3514A96A17}' ows_FSObjType='30;#0' ows_Created_x0020_Date='30;#2014-01-15 09:36:04' ows_FileLeafRef='30;#30_.000' ows_FileRef='30;#sites/rbs/DDM/Lists/prodoutcomecampaign/30_.000' ows_MetaInfo='30;#' ows_owshiddenversion='1' ows_Created='2014-01-15 09:36:04' />
   <z:row ows_ID='31' ows_Attachments='0' ows_Campaign_id='14' ows_Stage='priority' ows_Score='120' ows_Override='0' ows_StartDate='2014-02-03 00:00:00' ows_Roi='2.80' ows_RoiPass='1' ows_HasPreanalysis='1' ows_Nicpl='9.78' ows_NicplPass='1' ows_Nic='40,360' ows__ModerationStatus='0' ows__Level='1' ows_UniqueId='31;#{9B166496-AD53-4F4C-A391-D90131AE178A}' ows_FSObjType='31;#0' ows_Created_x0020_Date='31;#2014-01-15 09:36:04' ows_FileLeafRef='31;#31_.000' ows_FileRef='31;#sites/rbs/DDM/Lists/prodoutcomecampaign/31_.000' ows_MetaInfo='31;#' ows_owshiddenversion='1' ows_Created='2014-01-15 09:36:04' />
   <z:row ows_ID='32' ows_Attachments='0' ows_Campaign_id='18' ows_Stage='priority' ows_Score='780' ows_Override='0' ows_StartDate='2014-03-01 00:00:00' ows_Roi='3.90' ows_RoiPass='1' ows_HasPreanalysis='1' ows_Nicpl='3.90' ows_NicplPass='1' ows_Nic='273,000' ows__ModerationStatus='0' ows__Level='1' ows_UniqueId='32;#{67DB500A-8A8F-4628-B917-9FF36D547C6D}' ows_FSObjType='32;#0' ows_Created_x0020_Date='32;#2014-01-22 14:41:04' ows_FileLeafRef='32;#32_.000' ows_FileRef='32;#sites/rbs/DDM/Lists/prodoutcomecampaign/32_.000' ows_MetaInfo='32;#' ows_owshiddenversion='1' ows_Created='2014-01-22 14:41:04' />
   <z:row ows_ID='33' ows_Attachments='0' ows_Campaign_id='15' ows_Stage='to-pipeline' ows_Score='0' ows_Override='0' ows_StartDate='2014-01-24 00:00:00' ows_Roi='0.76' ows_RoiPass='0' ows_HasPreanalysis='1' ows_Nicpl='0.77' ows_NicplPass='0' ows_Nic='2,882' ows__ModerationStatus='0' ows__Level='1' ows_UniqueId='33;#{85EA6D85-5ECD-4590-B750-5FB71AB10043}' ows_FSObjType='33;#0' ows_Created_x0020_Date='33;#2014-01-22 14:41:04' ows_FileLeafRef='33;#33_.000' ows_FileRef='33;#sites/rbs/DDM/Lists/prodoutcomecampaign/33_.000' ows_MetaInfo='33;#' ows_owshiddenversion='1' ows_Created='2014-01-22 14:41:04' />
   <z:row ows_ID='34' ows_Attachments='0' ows_Campaign_id='14' ows_Stage='priority' ows_Score='680' ows_Override='0' ows_StartDate='2014-02-03 00:00:00' ows_Roi='2.80' ows_RoiPass='1' ows_HasPreanalysis='1' ows_Nicpl='9.78' ows_NicplPass='1' ows_Nic='40,360' ows__ModerationStatus='0' ows__Level='1' ows_UniqueId='34;#{3685312C-BB9E-4108-8E17-042F71032D9E}' ows_FSObjType='34;#0' ows_Created_x0020_Date='34;#2014-01-22 14:41:04' ows_FileLeafRef='34;#34_.000' ows_FileRef='34;#sites/rbs/DDM/Lists/prodoutcomecampaign/34_.000' ows_MetaInfo='34;#' ows_owshiddenversion='1' ows_Created='2014-01-22 14:41:04' />
   <z:row ows_ID='35' ows_Attachments='0' ows_Campaign_id='22' ows_Stage='priority' ows_Score='0' ows_Override='0' ows_StartDate='2014-01-15 00:00:00' ows_Roi='0.00' ows_RoiPass='0' ows_HasPreanalysis='0' ows_Nicpl='0.00' ows_NicplPass='0' ows_Nic='0' ows__ModerationStatus='0' ows__Level='1' ows_UniqueId='35;#{725E059D-2FC2-4BA2-A65A-7AB95680A4EF}' ows_FSObjType='35;#0' ows_Created_x0020_Date='35;#2014-01-22 14:41:04' ows_FileLeafRef='35;#35_.000' ows_FileRef='35;#sites/rbs/DDM/Lists/prodoutcomecampaign/35_.000' ows_MetaInfo='35;#' ows_owshiddenversion='1' ows_Created='2014-01-22 14:41:04' />
   <z:row ows_ID='36' ows_Attachments='0' ows_Campaign_id='30' ows_Stage='priority' ows_Score='0' ows_Override='0' ows_StartDate='2014-01-31 00:00:00' ows_Roi='0.00' ows_RoiPass='0' ows_HasPreanalysis='0' ows_Nicpl='0.00' ows_NicplPass='0' ows_Nic='0' ows__ModerationStatus='0' ows__Level='1' ows_UniqueId='36;#{C848C121-C94D-4BB1-B1BE-05AAB488F750}' ows_FSObjType='36;#0' ows_Created_x0020_Date='36;#2014-01-22 14:41:04' ows_FileLeafRef='36;#36_.000' ows_FileRef='36;#sites/rbs/DDM/Lists/prodoutcomecampaign/36_.000' ows_MetaInfo='36;#' ows_owshiddenversion='1' ows_Created='2014-01-22 14:41:04' />
   <z:row ows_ID='37' ows_Attachments='0' ows_Campaign_id='9' ows_Stage='priority' ows_Score='0' ows_Override='0' ows_StartDate='2014-02-05 00:00:00' ows_Roi='164.00' ows_RoiPass='1' ows_HasPreanalysis='1' ows_Nicpl='0.32' ows_NicplPass='0' ows_Nic='213,200' ows__ModerationStatus='0' ows__Level='1' ows_UniqueId='37;#{F8494B98-B5B2-4276-BE42-0587D33C2596}' ows_FSObjType='37;#0' ows_Created_x0020_Date='37;#2014-01-22 14:41:04' ows_FileLeafRef='37;#37_.000' ows_FileRef='37;#sites/rbs/DDM/Lists/prodoutcomecampaign/37_.000' ows_MetaInfo='37;#' ows_owshiddenversion='1' ows_Created='2014-01-22 14:41:04' />
   <z:row ows_ID='38' ows_Attachments='0' ows_Campaign_id='41' ows_Stage='priority' ows_Score='0' ows_Override='0' ows_StartDate='2014-02-14 00:00:00' ows_Roi='0.00' ows_RoiPass='0' ows_HasPreanalysis='0' ows_Nicpl='0.00' ows_NicplPass='0' ows_Nic='0' ows__ModerationStatus='0' ows__Level='1' ows_UniqueId='38;#{B1A2F86C-F5CB-4894-A44F-6D1E4C548E8A}' ows_FSObjType='38;#0' ows_Created_x0020_Date='38;#2014-01-22 14:41:04' ows_FileLeafRef='38;#38_.000' ows_FileRef='38;#sites/rbs/DDM/Lists/prodoutcomecampaign/38_.000' ows_MetaInfo='38;#' ows_owshiddenversion='1' ows_Created='2014-01-22 14:41:04' />
   <z:row ows_ID='39' ows_Attachments='0' ows_Campaign_id='37' ows_Stage='priority' ows_Score='0' ows_Override='0' ows_StartDate='2014-02-17 00:00:00' ows_Roi='0.00' ows_RoiPass='0' ows_HasPreanalysis='0' ows_Nicpl='0.00' ows_NicplPass='0' ows_Nic='0' ows__ModerationStatus='0' ows__Level='1' ows_UniqueId='39;#{CEEEBF55-329B-43CD-A682-3F5A6C1442D4}' ows_FSObjType='39;#0' ows_Created_x0020_Date='39;#2014-01-22 14:41:04' ows_FileLeafRef='39;#39_.000' ows_FileRef='39;#sites/rbs/DDM/Lists/prodoutcomecampaign/39_.000' ows_MetaInfo='39;#' ows_owshiddenversion='1' ows_Created='2014-01-22 14:41:04' />
   <z:row ows_ID='40' ows_Attachments='0' ows_Campaign_id='29' ows_Stage='priority' ows_Score='0' ows_Override='0' ows_StartDate='2014-03-01 00:00:00' ows_Roi='0.00' ows_RoiPass='0' ows_HasPreanalysis='0' ows_Nicpl='0.00' ows_NicplPass='0' ows_Nic='0' ows__ModerationStatus='0' ows__Level='1' ows_UniqueId='40;#{F87745F1-6BEE-4A48-B32E-DE137DAAB4B8}' ows_FSObjType='40;#0' ows_Created_x0020_Date='40;#2014-01-22 14:41:04' ows_FileLeafRef='40;#40_.000' ows_FileRef='40;#sites/rbs/DDM/Lists/prodoutcomecampaign/40_.000' ows_MetaInfo='40;#' ows_owshiddenversion='1' ows_Created='2014-01-22 14:41:04' />
   <z:row ows_ID='41' ows_Attachments='0' ows_Campaign_id='9' ows_Stage='to-pipeline' ows_Score='1' ows_Override='0' ows_StartDate='2014-02-05 00:00:00' ows_Roi='164.00' ows_RoiPass='1' ows_HasPreanalysis='1' ows_Nicpl='0.32' ows_NicplPass='0' ows_Nic='213,200' ows__ModerationStatus='0' ows__Level='1' ows_UniqueId='41;#{25F3B36E-F35F-4DE9-8973-63F36C38DEFF}' ows_FSObjType='41;#0' ows_Created_x0020_Date='41;#2014-01-28 10:09:51' ows_FileLeafRef='41;#41_.000' ows_FileRef='41;#sites/rbs/DDM/Lists/prodoutcomecampaign/41_.000' ows_MetaInfo='41;#' ows_owshiddenversion='1' ows_Created='2014-01-28 10:09:51' />
   <z:row ows_ID='42' ows_Attachments='0' ows_Campaign_id='14' ows_Stage='priority' ows_Score='590' ows_Override='0' ows_StartDate='2014-02-03 00:00:00' ows_Roi='2.80' ows_RoiPass='1' ows_HasPreanalysis='1' ows_Nicpl='9.78' ows_NicplPass='1' ows_Nic='40,360' ows__ModerationStatus='0' ows__Level='1' ows_UniqueId='42;#{DE931C1E-99AD-466A-A236-6D1FEBB1799F}' ows_FSObjType='42;#0' ows_Created_x0020_Date='42;#2014-01-28 10:09:52' ows_FileLeafRef='42;#42_.000' ows_FileRef='42;#sites/rbs/DDM/Lists/prodoutcomecampaign/42_.000' ows_MetaInfo='42;#' ows_owshiddenversion='1' ows_Created='2014-01-28 10:09:52' />
   <z:row ows_ID='43' ows_Attachments='0' ows_Campaign_id='18' ows_Stage='priority' ows_Score='690' ows_Override='0' ows_StartDate='2014-03-01 00:00:00' ows_Roi='3.90' ows_RoiPass='1' ows_HasPreanalysis='1' ows_Nicpl='3.90' ows_NicplPass='1' ows_Nic='273,000' ows__ModerationStatus='0' ows__Level='1' ows_UniqueId='43;#{C357C5DD-5FD5-4F24-9AD1-E7E898ACFDE6}' ows_FSObjType='43;#0' ows_Created_x0020_Date='43;#2014-01-28 10:09:52' ows_FileLeafRef='43;#43_.000' ows_FileRef='43;#sites/rbs/DDM/Lists/prodoutcomecampaign/43_.000' ows_MetaInfo='43;#' ows_owshiddenversion='1' ows_Created='2014-01-28 10:09:52' />
   <z:row ows_ID='44' ows_Attachments='0' ows_Campaign_id='22' ows_Stage='priority' ows_Score='0' ows_Override='0' ows_StartDate='2014-01-15 00:00:00' ows_Roi='0.00' ows_RoiPass='0' ows_HasPreanalysis='0' ows_Nicpl='0.00' ows_NicplPass='0' ows_Nic='0' ows__ModerationStatus='0' ows__Level='1' ows_UniqueId='44;#{59C48C7D-3237-4CDF-B344-D438CECC6641}' ows_FSObjType='44;#0' ows_Created_x0020_Date='44;#2014-01-28 10:09:52' ows_FileLeafRef='44;#44_.000' ows_FileRef='44;#sites/rbs/DDM/Lists/prodoutcomecampaign/44_.000' ows_MetaInfo='44;#' ows_owshiddenversion='1' ows_Created='2014-01-28 10:09:52' />
   <z:row ows_ID='45' ows_Attachments='0' ows_Campaign_id='41' ows_Stage='priority' ows_Score='0' ows_Override='0' ows_StartDate='2014-02-14 00:00:00' ows_Roi='0.00' ows_RoiPass='0' ows_HasPreanalysis='0' ows_Nicpl='0.00' ows_NicplPass='0' ows_Nic='0' ows__ModerationStatus='0' ows__Level='1' ows_UniqueId='45;#{B4980636-FBBD-4730-B662-0ADAB20381DE}' ows_FSObjType='45;#0' ows_Created_x0020_Date='45;#2014-01-28 10:09:52' ows_FileLeafRef='45;#45_.000' ows_FileRef='45;#sites/rbs/DDM/Lists/prodoutcomecampaign/45_.000' ows_MetaInfo='45;#' ows_owshiddenversion='1' ows_Created='2014-01-28 10:09:52' />
   <z:row ows_ID='46' ows_Attachments='0' ows_Campaign_id='37' ows_Stage='priority' ows_Score='0' ows_Override='0' ows_StartDate='2014-02-17 00:00:00' ows_Roi='0.00' ows_RoiPass='0' ows_HasPreanalysis='0' ows_Nicpl='0.00' ows_NicplPass='0' ows_Nic='0' ows__ModerationStatus='0' ows__Level='1' ows_UniqueId='46;#{BD4EA49C-F4F4-4305-ADA8-3B30C2E80168}' ows_FSObjType='46;#0' ows_Created_x0020_Date='46;#2014-01-28 10:09:52' ows_FileLeafRef='46;#46_.000' ows_FileRef='46;#sites/rbs/DDM/Lists/prodoutcomecampaign/46_.000' ows_MetaInfo='46;#' ows_owshiddenversion='1' ows_Created='2014-01-28 10:09:52' />
   <z:row ows_ID='47' ows_Attachments='0' ows_Campaign_id='30' ows_Stage='priority' ows_Score='0' ows_Override='0' ows_StartDate='2014-01-31 00:00:00' ows_Roi='0.00' ows_RoiPass='0' ows_HasPreanalysis='0' ows_Nicpl='0.00' ows_NicplPass='0' ows_Nic='0' ows__ModerationStatus='0' ows__Level='1' ows_UniqueId='47;#{AC1EC6BE-F20E-49D7-AC43-FE6ED7D6CFF0}' ows_FSObjType='47;#0' ows_Created_x0020_Date='47;#2014-01-28 10:09:52' ows_FileLeafRef='47;#47_.000' ows_FileRef='47;#sites/rbs/DDM/Lists/prodoutcomecampaign/47_.000' ows_MetaInfo='47;#' ows_owshiddenversion='1' ows_Created='2014-01-28 10:09:52' />
   <z:row ows_ID='48' ows_Attachments='0' ows_Campaign_id='29' ows_Stage='priority' ows_Score='0' ows_Override='0' ows_StartDate='2014-03-01 00:00:00' ows_Roi='0.00' ows_RoiPass='0' ows_HasPreanalysis='0' ows_Nicpl='0.00' ows_NicplPass='0' ows_Nic='0' ows__ModerationStatus='0' ows__Level='1' ows_UniqueId='48;#{5472B9D4-0F9C-4180-A665-CD489481821E}' ows_FSObjType='48;#0' ows_Created_x0020_Date='48;#2014-01-28 10:09:52' ows_FileLeafRef='48;#48_.000' ows_FileRef='48;#sites/rbs/DDM/Lists/prodoutcomecampaign/48_.000' ows_MetaInfo='48;#' ows_owshiddenversion='1' ows_Created='2014-01-28 10:09:52' />
   <z:row ows_ID='49' ows_Attachments='0' ows_Campaign_id='22' ows_Stage='to-pipeline' ows_Score='1' ows_Override='1' ows_StartDate='2014-01-15 00:00:00' ows_Roi='0.00' ows_RoiPass='0' ows_HasPreanalysis='0' ows_Nicpl='0.00' ows_NicplPass='0' ows_Nic='0' ows__ModerationStatus='0' ows__Level='1' ows_UniqueId='49;#{E3C549ED-B71F-4B31-9877-3A8D8154A0F3}' ows_FSObjType='49;#0' ows_Created_x0020_Date='49;#2014-01-28 10:10:39' ows_FileLeafRef='49;#49_.000' ows_FileRef='49;#sites/rbs/DDM/Lists/prodoutcomecampaign/49_.000' ows_MetaInfo='49;#' ows_owshiddenversion='1' ows_Created='2014-01-28 10:10:39' />
   <z:row ows_ID='50' ows_Attachments='0' ows_Campaign_id='18' ows_Stage='priority' ows_Score='630' ows_Override='0' ows_StartDate='2014-03-01 00:00:00' ows_Roi='3.90' ows_RoiPass='1' ows_HasPreanalysis='1' ows_Nicpl='3.90' ows_NicplPass='1' ows_Nic='273,000' ows__ModerationStatus='0' ows__Level='1' ows_UniqueId='50;#{B4F463E8-2BDF-412A-A75C-102576C296E9}' ows_FSObjType='50;#0' ows_Created_x0020_Date='50;#2014-01-28 10:10:39' ows_FileLeafRef='50;#50_.000' ows_FileRef='50;#sites/rbs/DDM/Lists/prodoutcomecampaign/50_.000' ows_MetaInfo='50;#' ows_owshiddenversion='1' ows_Created='2014-01-28 10:10:39' />
   <z:row ows_ID='51' ows_Attachments='0' ows_Campaign_id='41' ows_Stage='priority' ows_Score='0' ows_Override='0' ows_StartDate='2014-02-14 00:00:00' ows_Roi='0.00' ows_RoiPass='0' ows_HasPreanalysis='0' ows_Nicpl='0.00' ows_NicplPass='0' ows_Nic='0' ows__ModerationStatus='0' ows__Level='1' ows_UniqueId='51;#{110AD149-4779-41B1-8577-91657991AD90}' ows_FSObjType='51;#0' ows_Created_x0020_Date='51;#2014-01-28 10:10:39' ows_FileLeafRef='51;#51_.000' ows_FileRef='51;#sites/rbs/DDM/Lists/prodoutcomecampaign/51_.000' ows_MetaInfo='51;#' ows_owshiddenversion='1' ows_Created='2014-01-28 10:10:39' />
   <z:row ows_ID='52' ows_Attachments='0' ows_Campaign_id='14' ows_Stage='priority' ows_Score='570' ows_Override='0' ows_StartDate='2014-02-03 00:00:00' ows_Roi='2.80' ows_RoiPass='1' ows_HasPreanalysis='1' ows_Nicpl='9.78' ows_NicplPass='1' ows_Nic='40,360' ows__ModerationStatus='0' ows__Level='1' ows_UniqueId='52;#{E5958100-9E77-46B3-BC07-EC427CFE736F}' ows_FSObjType='52;#0' ows_Created_x0020_Date='52;#2014-01-28 10:10:39' ows_FileLeafRef='52;#52_.000' ows_FileRef='52;#sites/rbs/DDM/Lists/prodoutcomecampaign/52_.000' ows_MetaInfo='52;#' ows_owshiddenversion='1' ows_Created='2014-01-28 10:10:39' />
   <z:row ows_ID='53' ows_Attachments='0' ows_Campaign_id='30' ows_Stage='priority' ows_Score='0' ows_Override='0' ows_StartDate='2014-01-31 00:00:00' ows_Roi='0.00' ows_RoiPass='0' ows_HasPreanalysis='0' ows_Nicpl='0.00' ows_NicplPass='0' ows_Nic='0' ows__ModerationStatus='0' ows__Level='1' ows_UniqueId='53;#{A9FA4489-0D05-42C1-8F04-8B8811CEFFBF}' ows_FSObjType='53;#0' ows_Created_x0020_Date='53;#2014-01-28 10:10:39' ows_FileLeafRef='53;#53_.000' ows_FileRef='53;#sites/rbs/DDM/Lists/prodoutcomecampaign/53_.000' ows_MetaInfo='53;#' ows_owshiddenversion='1' ows_Created='2014-01-28 10:10:39' />
   <z:row ows_ID='54' ows_Attachments='0' ows_Campaign_id='29' ows_Stage='priority' ows_Score='0' ows_Override='0' ows_StartDate='2014-03-01 00:00:00' ows_Roi='0.00' ows_RoiPass='0' ows_HasPreanalysis='0' ows_Nicpl='0.00' ows_NicplPass='0' ows_Nic='0' ows__ModerationStatus='0' ows__Level='1' ows_UniqueId='54;#{5839990C-5AAC-4A40-AB96-126EF0C87970}' ows_FSObjType='54;#0' ows_Created_x0020_Date='54;#2014-01-28 10:10:40' ows_FileLeafRef='54;#54_.000' ows_FileRef='54;#sites/rbs/DDM/Lists/prodoutcomecampaign/54_.000' ows_MetaInfo='54;#' ows_owshiddenversion='1' ows_Created='2014-01-28 10:10:40' />
   <z:row ows_ID='55' ows_Attachments='0' ows_Campaign_id='37' ows_Stage='priority' ows_Score='0' ows_Override='0' ows_StartDate='2014-02-17 00:00:00' ows_Roi='0.00' ows_RoiPass='0' ows_HasPreanalysis='0' ows_Nicpl='0.00' ows_NicplPass='0' ows_Nic='0' ows__ModerationStatus='0' ows__Level='1' ows_UniqueId='55;#{937E4982-A18E-4F05-A384-A0ED1FD786B0}' ows_FSObjType='55;#0' ows_Created_x0020_Date='55;#2014-01-28 10:10:39' ows_FileLeafRef='55;#55_.000' ows_FileRef='55;#sites/rbs/DDM/Lists/prodoutcomecampaign/55_.000' ows_MetaInfo='55;#' ows_owshiddenversion='1' ows_Created='2014-01-28 10:10:39' />
   <z:row ows_ID='56' ows_Attachments='0' ows_Campaign_id='43' ows_Stage='to-pipeline' ows_Score='1' ows_Override='1' ows_StartDate='2014-02-04 00:00:00' ows_Roi='0.00' ows_RoiPass='0' ows_HasPreanalysis='0' ows_Nicpl='0.00' ows_NicplPass='0' ows_Nic='0' ows__ModerationStatus='0' ows__Level='1' ows_UniqueId='56;#{8E554222-6D65-4564-B741-A1417ED13576}' ows_FSObjType='56;#0' ows_Created_x0020_Date='56;#2014-01-29 15:34:03' ows_FileLeafRef='56;#56_.000' ows_FileRef='56;#sites/rbs/DDM/Lists/prodoutcomecampaign/56_.000' ows_MetaInfo='56;#' ows_owshiddenversion='1' ows_Created='2014-01-29 15:34:03' />
   <z:row ows_ID='57' ows_Attachments='0' ows_Campaign_id='30' ows_Stage='to-pipeline' ows_Score='1' ows_Override='1' ows_StartDate='2014-01-31 00:00:00' ows_Roi='0.00' ows_RoiPass='0' ows_HasPreanalysis='0' ows_Nicpl='0.00' ows_NicplPass='0' ows_Nic='0' ows__ModerationStatus='0' ows__Level='1' ows_UniqueId='57;#{8E36B471-DB39-49C8-B85B-F8CE999E3F68}' ows_FSObjType='57;#0' ows_Created_x0020_Date='57;#2014-01-29 15:34:03' ows_FileLeafRef='57;#57_.000' ows_FileRef='57;#sites/rbs/DDM/Lists/prodoutcomecampaign/57_.000' ows_MetaInfo='57;#' ows_owshiddenversion='1' ows_Created='2014-01-29 15:34:03' />
   <z:row ows_ID='58' ows_Attachments='0' ows_Campaign_id='21' ows_Stage='to-pipeline' ows_Score='720' ows_Override='0' ows_StartDate='2014-01-31 00:00:00' ows_Roi='8.98' ows_RoiPass='1' ows_HasPreanalysis='1' ows_Nicpl='6.41' ows_NicplPass='1' ows_Nic='3,123,709' ows__ModerationStatus='0' ows__Level='1' ows_UniqueId='58;#{30779B94-8748-4E43-A65E-E91F681465F0}' ows_FSObjType='58;#0' ows_Created_x0020_Date='58;#2014-01-29 15:34:03' ows_FileLeafRef='58;#58_.000' ows_FileRef='58;#sites/rbs/DDM/Lists/prodoutcomecampaign/58_.000' ows_MetaInfo='58;#' ows_owshiddenversion='1' ows_Created='2014-01-29 15:34:03' />
   <z:row ows_ID='59' ows_Attachments='0' ows_Campaign_id='18' ows_Stage='to-pipeline' ows_Score='640' ows_Override='0' ows_StartDate='2014-03-01 00:00:00' ows_Roi='3.90' ows_RoiPass='1' ows_HasPreanalysis='1' ows_Nicpl='3.90' ows_NicplPass='1' ows_Nic='273,000' ows__ModerationStatus='0' ows__Level='1' ows_UniqueId='59;#{BD1B0F12-7EEF-4E80-B35C-F5C087B7F86D}' ows_FSObjType='59;#0' ows_Created_x0020_Date='59;#2014-01-29 15:34:03' ows_FileLeafRef='59;#59_.000' ows_FileRef='59;#sites/rbs/DDM/Lists/prodoutcomecampaign/59_.000' ows_MetaInfo='59;#' ows_owshiddenversion='1' ows_Created='2014-01-29 15:34:03' />
   <z:row ows_ID='60' ows_Attachments='0' ows_Campaign_id='14' ows_Stage='to-pipeline' ows_Score='590' ows_Override='0' ows_StartDate='2014-02-03 00:00:00' ows_Roi='2.80' ows_RoiPass='1' ows_HasPreanalysis='1' ows_Nicpl='9.78' ows_NicplPass='1' ows_Nic='40,360' ows__ModerationStatus='0' ows__Level='1' ows_UniqueId='60;#{4394488F-FBAA-476C-B42C-19EB66842AFF}' ows_FSObjType='60;#0' ows_Created_x0020_Date='60;#2014-01-29 15:34:03' ows_FileLeafRef='60;#60_.000' ows_FileRef='60;#sites/rbs/DDM/Lists/prodoutcomecampaign/60_.000' ows_MetaInfo='60;#' ows_owshiddenversion='1' ows_Created='2014-01-29 15:34:03' />
   <z:row ows_ID='61' ows_Attachments='0' ows_Campaign_id='41' ows_Stage='to-pipeline' ows_Score='1' ows_Override='1' ows_StartDate='2014-02-14 00:00:00' ows_Roi='0.00' ows_RoiPass='0' ows_HasPreanalysis='0' ows_Nicpl='0.00' ows_NicplPass='0' ows_Nic='0' ows__ModerationStatus='0' ows__Level='1' ows_UniqueId='61;#{9251F995-C6CC-44AD-AE29-7670FD209C04}' ows_FSObjType='61;#0' ows_Created_x0020_Date='61;#2014-01-29 15:34:03' ows_FileLeafRef='61;#61_.000' ows_FileRef='61;#sites/rbs/DDM/Lists/prodoutcomecampaign/61_.000' ows_MetaInfo='61;#' ows_owshiddenversion='1' ows_Created='2014-01-29 15:34:03' />
   <z:row ows_ID='62' ows_Attachments='0' ows_Campaign_id='37' ows_Stage='to-pipeline' ows_Score='1' ows_Override='1' ows_StartDate='2014-02-17 00:00:00' ows_Roi='0.00' ows_RoiPass='0' ows_HasPreanalysis='0' ows_Nicpl='0.00' ows_NicplPass='0' ows_Nic='0' ows__ModerationStatus='0' ows__Level='1' ows_UniqueId='62;#{21C4A388-FDD9-40EA-97A0-B454BC90EAC4}' ows_FSObjType='62;#0' ows_Created_x0020_Date='62;#2014-01-29 15:34:03' ows_FileLeafRef='62;#62_.000' ows_FileRef='62;#sites/rbs/DDM/Lists/prodoutcomecampaign/62_.000' ows_MetaInfo='62;#' ows_owshiddenversion='1' ows_Created='2014-01-29 15:34:03' />
   <z:row ows_ID='63' ows_Attachments='0' ows_Campaign_id='29' ows_Stage='to-pipeline' ows_Score='1' ows_Override='1' ows_StartDate='2014-03-01 00:00:00' ows_Roi='0.00' ows_RoiPass='0' ows_HasPreanalysis='0' ows_Nicpl='0.00' ows_NicplPass='0' ows_Nic='0' ows__ModerationStatus='0' ows__Level='1' ows_UniqueId='63;#{4881981D-BAB4-4F2D-8865-1DE454DFBC75}' ows_FSObjType='63;#0' ows_Created_x0020_Date='63;#2014-01-29 15:34:03' ows_FileLeafRef='63;#63_.000' ows_FileRef='63;#sites/rbs/DDM/Lists/prodoutcomecampaign/63_.000' ows_MetaInfo='63;#' ows_owshiddenversion='1' ows_Created='2014-01-29 15:34:03' />
   <z:row ows_ID='64' ows_Attachments='0' ows_Campaign_id='16' ows_Stage='to-pipeline' ows_Score='850' ows_Override='0' ows_StartDate='2014-04-01 00:00:00' ows_Roi='67.85' ows_RoiPass='1' ows_HasPreanalysis='1' ows_Nicpl='50.65' ows_NicplPass='1' ows_Nic='6,989,048' ows__ModerationStatus='0' ows__Level='1' ows_UniqueId='64;#{1FA00EF0-19C9-4E80-A47E-D4E4FF5F8DE9}' ows_FSObjType='64;#0' ows_Created_x0020_Date='64;#2014-01-29 15:34:03' ows_FileLeafRef='64;#64_.000' ows_FileRef='64;#sites/rbs/DDM/Lists/prodoutcomecampaign/64_.000' ows_MetaInfo='64;#' ows_owshiddenversion='1' ows_Created='2014-01-29 15:34:03' />
   <z:row ows_ID='65' ows_Attachments='0' ows_Campaign_id='54' ows_Stage='priority' ows_Score='0' ows_Override='0' ows_StartDate='2014-02-07 00:00:00' ows_Roi='0.00' ows_RoiPass='0' ows_HasPreanalysis='0' ows_Nicpl='0.00' ows_NicplPass='0' ows_Nic='0' ows__ModerationStatus='0' ows__Level='1' ows_UniqueId='65;#{47365668-8C07-4D82-8E94-BFC4B49D4AB4}' ows_FSObjType='65;#0' ows_Created_x0020_Date='65;#2014-01-30 09:56:23' ows_FileLeafRef='65;#65_.000' ows_FileRef='65;#sites/rbs/DDM/Lists/prodoutcomecampaign/65_.000' ows_MetaInfo='65;#' ows_owshiddenversion='1' ows_Created='2014-01-30 09:56:23' />
   <z:row ows_ID='66' ows_Attachments='0' ows_Campaign_id='54' ows_Stage='priority' ows_Score='0' ows_Override='0' ows_StartDate='2014-02-07 00:00:00' ows_Roi='0.00' ows_RoiPass='0' ows_HasPreanalysis='0' ows_Nicpl='0.00' ows_NicplPass='0' ows_Nic='0' ows__ModerationStatus='0' ows__Level='1' ows_UniqueId='66;#{51F265FA-B062-4AF7-A491-EED768EF5B27}' ows_FSObjType='66;#0' ows_Created_x0020_Date='66;#2014-01-30 09:57:37' ows_FileLeafRef='66;#66_.000' ows_FileRef='66;#sites/rbs/DDM/Lists/prodoutcomecampaign/66_.000' ows_MetaInfo='66;#' ows_owshiddenversion='1' ows_Created='2014-01-30 09:57:37' />
   <z:row ows_ID='67' ows_Attachments='0' ows_Campaign_id='54' ows_Stage='to-pipeline' ows_Score='1' ows_Override='1' ows_StartDate='2014-02-07 00:00:00' ows_Roi='0.00' ows_RoiPass='0' ows_HasPreanalysis='0' ows_Nicpl='0.00' ows_NicplPass='0' ows_Nic='0' ows__ModerationStatus='0' ows__Level='1' ows_UniqueId='67;#{1259206C-F888-4D04-94CB-D6BCB118B55A}' ows_FSObjType='67;#0' ows_Created_x0020_Date='67;#2014-01-30 09:58:39' ows_FileLeafRef='67;#67_.000' ows_FileRef='67;#sites/rbs/DDM/Lists/prodoutcomecampaign/67_.000' ows_MetaInfo='67;#' ows_owshiddenversion='1' ows_Created='2014-01-30 09:58:39' />
   <z:row ows_ID='68' ows_Attachments='0' ows_Campaign_id='42' ows_Stage='to-pipeline' ows_Score='1340' ows_Override='0' ows_StartDate='2014-02-15 00:00:00' ows_Roi='926.00' ows_RoiPass='1' ows_HasPreanalysis='1' ows_Nicpl='9.26' ows_NicplPass='1' ows_Nic='786,730' ows__ModerationStatus='0' ows__Level='1' ows_UniqueId='68;#{F2D110EF-55EB-4D0D-9E10-A9A3DD0FA5CA}' ows_FSObjType='68;#0' ows_Created_x0020_Date='68;#2014-02-12 13:52:57' ows_FileLeafRef='68;#68_.000' ows_FileRef='68;#sites/rbs/DDM/Lists/prodoutcomecampaign/68_.000' ows_MetaInfo='68;#' ows_owshiddenversion='1' ows_Created='2014-02-12 13:52:57' />
   <z:row ows_ID='69' ows_Attachments='0' ows_Campaign_id='49' ows_Stage='to-pipeline' ows_Score='2' ows_Override='1' ows_StartDate='2014-05-01 00:00:00' ows_Roi='0.00' ows_RoiPass='0' ows_HasPreanalysis='0' ows_Nicpl='0.00' ows_NicplPass='0' ows_Nic='0' ows__ModerationStatus='0' ows__Level='1' ows_UniqueId='69;#{6890D7A3-934D-4188-8E7C-FC111CA6CB7F}' ows_FSObjType='69;#0' ows_Created_x0020_Date='69;#2014-02-12 13:52:57' ows_FileLeafRef='69;#69_.000' ows_FileRef='69;#sites/rbs/DDM/Lists/prodoutcomecampaign/69_.000' ows_MetaInfo='69;#' ows_owshiddenversion='1' ows_Created='2014-02-12 13:52:57' />
   <z:row ows_ID='70' ows_Attachments='0' ows_Campaign_id='58' ows_Stage='to-pipeline' ows_Score='1220' ows_Override='0' ows_StartDate='2014-03-01 00:00:00' ows_Roi='315.27' ows_RoiPass='1' ows_HasPreanalysis='1' ows_Nicpl='3.15' ows_NicplPass='1' ows_Nic='945,810' ows__ModerationStatus='0' ows__Level='1' ows_UniqueId='70;#{F28D6937-A0C1-42B3-A239-5664C73FD860}' ows_FSObjType='70;#0' ows_Created_x0020_Date='70;#2014-02-12 13:52:57' ows_FileLeafRef='70;#70_.000' ows_FileRef='70;#sites/rbs/DDM/Lists/prodoutcomecampaign/70_.000' ows_MetaInfo='70;#' ows_owshiddenversion='1' ows_Created='2014-02-12 13:52:57' />
   <z:row ows_ID='71' ows_Attachments='0' ows_Campaign_id='40' ows_Stage='to-pipeline' ows_Score='1470' ows_Override='0' ows_StartDate='2014-02-18 00:00:00' ows_Roi='2,171.28' ows_RoiPass='1' ows_HasPreanalysis='1' ows_Nicpl='3.69' ows_NicplPass='1' ows_Nic='8,685,120' ows__ModerationStatus='0' ows__Level='1' ows_UniqueId='71;#{1289DBB0-E77E-4185-AEE9-D037C3E36EDA}' ows_FSObjType='71;#0' ows_Created_x0020_Date='71;#2014-02-12 13:52:57' ows_FileLeafRef='71;#71_.000' ows_FileRef='71;#sites/rbs/DDM/Lists/prodoutcomecampaign/71_.000' ows_MetaInfo='71;#' ows_owshiddenversion='1' ows_Created='2014-02-12 13:52:57' />
   <z:row ows_ID='72' ows_Attachments='0' ows_Campaign_id='59' ows_Stage='to-pipeline' ows_Score='1160' ows_Override='0' ows_StartDate='2014-03-01 00:00:00' ows_Roi='63.00' ows_RoiPass='1' ows_HasPreanalysis='1' ows_Nicpl='6.30' ows_NicplPass='1' ows_Nic='5,499,585' ows__ModerationStatus='0' ows__Level='1' ows_UniqueId='72;#{A33BE05A-1C8B-457C-A9B9-3EBB28B22926}' ows_FSObjType='72;#0' ows_Created_x0020_Date='72;#2014-02-12 13:52:57' ows_FileLeafRef='72;#72_.000' ows_FileRef='72;#sites/rbs/DDM/Lists/prodoutcomecampaign/72_.000' ows_MetaInfo='72;#' ows_owshiddenversion='1' ows_Created='2014-02-12 13:52:57' />
   <z:row ows_ID='73' ows_Attachments='0' ows_Campaign_id='60' ows_Stage='to-pipeline' ows_Score='1010' ows_Override='0' ows_StartDate='2014-04-02 00:00:00' ows_Roi='77.41' ows_RoiPass='1' ows_HasPreanalysis='1' ows_Nicpl='2.02' ows_NicplPass='1' ows_Nic='3,034,650' ows__ModerationStatus='0' ows__Level='1' ows_UniqueId='73;#{B3CBDD7F-8DEE-47ED-BFF9-54A305A4269E}' ows_FSObjType='73;#0' ows_Created_x0020_Date='73;#2014-02-12 13:52:57' ows_FileLeafRef='73;#73_.000' ows_FileRef='73;#sites/rbs/DDM/Lists/prodoutcomecampaign/73_.000' ows_MetaInfo='73;#' ows_owshiddenversion='1' ows_Created='2014-02-12 13:52:57' />
   <z:row ows_ID='74' ows_Attachments='0' ows_Campaign_id='38' ows_Stage='to-pipeline' ows_Score='970' ows_Override='0' ows_StartDate='2014-03-07 00:00:00' ows_Roi='13.16' ows_RoiPass='1' ows_HasPreanalysis='1' ows_Nicpl='7.44' ows_NicplPass='1' ows_Nic='617,300' ows__ModerationStatus='0' ows__Level='1' ows_UniqueId='74;#{E441D8C3-DD91-4743-87BA-5817782859FE}' ows_FSObjType='74;#0' ows_Created_x0020_Date='74;#2014-02-12 13:52:57' ows_FileLeafRef='74;#74_.000' ows_FileRef='74;#sites/rbs/DDM/Lists/prodoutcomecampaign/74_.000' ows_MetaInfo='74;#' ows_owshiddenversion='1' ows_Created='2014-02-12 13:52:57' />
   <z:row ows_ID='75' ows_Attachments='0' ows_Campaign_id='52' ows_Stage='to-pipeline' ows_Score='960' ows_Override='0' ows_StartDate='2014-02-15 00:00:00' ows_Roi='9.03' ows_RoiPass='1' ows_HasPreanalysis='1' ows_Nicpl='2.48' ows_NicplPass='1' ows_Nic='4,513,200' ows__ModerationStatus='0' ows__Level='1' ows_UniqueId='75;#{22B02B00-504C-4A26-A44C-6C6A51B3559A}' ows_FSObjType='75;#0' ows_Created_x0020_Date='75;#2014-02-12 13:52:57' ows_FileLeafRef='75;#75_.000' ows_FileRef='75;#sites/rbs/DDM/Lists/prodoutcomecampaign/75_.000' ows_MetaInfo='75;#' ows_owshiddenversion='1' ows_Created='2014-02-12 13:52:57' />
   <z:row ows_ID='76' ows_Attachments='0' ows_Campaign_id='5' ows_Stage='to-pipeline' ows_Score='940' ows_Override='0' ows_StartDate='2014-02-10 00:00:00' ows_Roi='470.00' ows_RoiPass='1' ows_HasPreanalysis='1' ows_Nicpl='4.70' ows_NicplPass='1' ows_Nic='47,000' ows__ModerationStatus='0' ows__Level='1' ows_UniqueId='76;#{653AA3E4-D4CC-47B2-A39A-4E8CCAC5732A}' ows_FSObjType='76;#0' ows_Created_x0020_Date='76;#2014-02-12 13:52:57' ows_FileLeafRef='76;#76_.000' ows_FileRef='76;#sites/rbs/DDM/Lists/prodoutcomecampaign/76_.000' ows_MetaInfo='76;#' ows_owshiddenversion='1' ows_Created='2014-02-12 13:52:57' />
   <z:row ows_ID='77' ows_Attachments='0' ows_Campaign_id='70' ows_Stage='to-pipeline' ows_Score='720' ows_Override='0' ows_StartDate='2014-02-28 00:00:00' ows_Roi='51.87' ows_RoiPass='1' ows_HasPreanalysis='1' ows_Nicpl='2.44' ows_NicplPass='1' ows_Nic='52,466' ows__ModerationStatus='0' ows__Level='1' ows_UniqueId='77;#{779F60C9-1ABE-40E0-9206-1FEA2EF221F5}' ows_FSObjType='77;#0' ows_Created_x0020_Date='77;#2014-02-12 13:52:57' ows_FileLeafRef='77;#77_.000' ows_FileRef='77;#sites/rbs/DDM/Lists/prodoutcomecampaign/77_.000' ows_MetaInfo='77;#' ows_owshiddenversion='1' ows_Created='2014-02-12 13:52:57' />
   <z:row ows_ID='78' ows_Attachments='0' ows_Campaign_id='45' ows_Stage='to-pipeline' ows_Score='2' ows_Override='0' ows_StartDate='2014-03-10 00:00:00' ows_Roi='282.83' ows_RoiPass='1' ows_HasPreanalysis='1' ows_Nicpl='1.70' ows_NicplPass='0' ows_Nic='577,784' ows__ModerationStatus='0' ows__Level='1' ows_UniqueId='78;#{91461087-1D7A-4B82-A39C-07D595D59EEB}' ows_FSObjType='78;#0' ows_Created_x0020_Date='78;#2014-02-12 13:52:57' ows_FileLeafRef='78;#78_.000' ows_FileRef='78;#sites/rbs/DDM/Lists/prodoutcomecampaign/78_.000' ows_MetaInfo='78;#' ows_owshiddenversion='1' ows_Created='2014-02-12 13:52:57' />
   <z:row ows_ID='79' ows_Attachments='0' ows_Campaign_id='50' ows_Stage='priority' ows_Score='2' ows_Override='0' ows_StartDate='2014-02-28 00:00:00' ows_Roi='1.01' ows_RoiPass='0' ows_HasPreanalysis='1' ows_Nicpl='0.15' ows_NicplPass='0' ows_Nic='100,967' ows__ModerationStatus='0' ows__Level='1' ows_UniqueId='79;#{0D9C2F8B-D7AB-4937-88C6-5905EA7F4C2C}' ows_FSObjType='79;#0' ows_Created_x0020_Date='79;#2014-02-12 13:52:57' ows_FileLeafRef='79;#79_.000' ows_FileRef='79;#sites/rbs/DDM/Lists/prodoutcomecampaign/79_.000' ows_MetaInfo='79;#' ows_owshiddenversion='1' ows_Created='2014-02-12 13:52:57' />
   <z:row ows_ID='80' ows_Attachments='0' ows_Campaign_id='63' ows_Stage='priority' ows_Score='2' ows_Override='0' ows_StartDate='2014-03-03 00:00:00' ows_Roi='88.41' ows_RoiPass='1' ows_HasPreanalysis='1' ows_Nicpl='1.19' ows_NicplPass='0' ows_Nic='429,660' ows__ModerationStatus='0' ows__Level='1' ows_UniqueId='80;#{63D68CB4-50DA-49E0-A904-7E770E6326B6}' ows_FSObjType='80;#0' ows_Created_x0020_Date='80;#2014-02-12 13:52:58' ows_FileLeafRef='80;#80_.000' ows_FileRef='80;#sites/rbs/DDM/Lists/prodoutcomecampaign/80_.000' ows_MetaInfo='80;#' ows_owshiddenversion='1' ows_Created='2014-02-12 13:52:58' />
   <z:row ows_ID='81' ows_Attachments='0' ows_Campaign_id='24' ows_Stage='priority' ows_Score='2' ows_Override='0' ows_StartDate='2014-03-10 00:00:00' ows_Roi='6.68' ows_RoiPass='1' ows_HasPreanalysis='1' ows_Nicpl='0.66' ows_NicplPass='0' ows_Nic='26,876' ows__ModerationStatus='0' ows__Level='1' ows_UniqueId='81;#{44E9B48C-B739-4A70-9334-6567C22C14A7}' ows_FSObjType='81;#0' ows_Created_x0020_Date='81;#2014-02-12 13:52:58' ows_FileLeafRef='81;#81_.000' ows_FileRef='81;#sites/rbs/DDM/Lists/prodoutcomecampaign/81_.000' ows_MetaInfo='81;#' ows_owshiddenversion='1' ows_Created='2014-02-12 13:52:58' />
   <z:row ows_ID='82' ows_Attachments='0' ows_Campaign_id='25' ows_Stage='priority' ows_Score='1' ows_Override='0' ows_StartDate='2014-02-14 00:00:00' ows_Roi='0.00' ows_RoiPass='0' ows_HasPreanalysis='1' ows_Nicpl='0.00' ows_NicplPass='0' ows_Nic='0' ows__ModerationStatus='0' ows__Level='1' ows_UniqueId='82;#{0894FE11-9E2B-4308-8003-6C877CF75DB4}' ows_FSObjType='82;#0' ows_Created_x0020_Date='82;#2014-02-12 13:52:57' ows_FileLeafRef='82;#82_.000' ows_FileRef='82;#sites/rbs/DDM/Lists/prodoutcomecampaign/82_.000' ows_MetaInfo='82;#' ows_owshiddenversion='1' ows_Created='2014-02-12 13:52:57' />
   <z:row ows_ID='83' ows_Attachments='0' ows_Campaign_id='43' ows_Stage='priority' ows_Score='0' ows_Override='0' ows_StartDate='2014-02-04 00:00:00' ows_Roi='0.00' ows_RoiPass='0' ows_HasPreanalysis='0' ows_Nicpl='0.00' ows_NicplPass='0' ows_Nic='0' ows__ModerationStatus='0' ows__Level='1' ows_UniqueId='83;#{B3F6AB6B-DDDB-4E61-9C32-F76D4FAC6FC9}' ows_FSObjType='83;#0' ows_Created_x0020_Date='83;#2014-02-12 13:52:57' ows_FileLeafRef='83;#83_.000' ows_FileRef='83;#sites/rbs/DDM/Lists/prodoutcomecampaign/83_.000' ows_MetaInfo='83;#' ows_owshiddenversion='1' ows_Created='2014-02-12 13:52:57' />
   <z:row ows_ID='84' ows_Attachments='0' ows_Campaign_id='50' ows_Stage='priority' ows_Score='2' ows_Override='0' ows_StartDate='2014-02-28 00:00:00' ows_Roi='1.01' ows_RoiPass='0' ows_HasPreanalysis='1' ows_Nicpl='0.15' ows_NicplPass='0' ows_Nic='100,967' ows__ModerationStatus='0' ows__Level='1' ows_UniqueId='84;#{3846E804-70D8-4E67-8911-BFB78B83818A}' ows_FSObjType='84;#0' ows_Created_x0020_Date='84;#2014-02-12 14:04:13' ows_FileLeafRef='84;#84_.000' ows_FileRef='84;#sites/rbs/DDM/Lists/prodoutcomecampaign/84_.000' ows_MetaInfo='84;#' ows_owshiddenversion='1' ows_Created='2014-02-12 14:04:13' />
   <z:row ows_ID='85' ows_Attachments='0' ows_Campaign_id='24' ows_Stage='to-pipeline' ows_Score='2' ows_Override='0' ows_StartDate='2014-03-10 00:00:00' ows_Roi='6.68' ows_RoiPass='1' ows_HasPreanalysis='1' ows_Nicpl='0.66' ows_NicplPass='0' ows_Nic='26,876' ows__ModerationStatus='0' ows__Level='1' ows_UniqueId='85;#{FA850044-7CC5-42B2-BC6F-17C947739CD4}' ows_FSObjType='85;#0' ows_Created_x0020_Date='85;#2014-02-12 14:04:13' ows_FileLeafRef='85;#85_.000' ows_FileRef='85;#sites/rbs/DDM/Lists/prodoutcomecampaign/85_.000' ows_MetaInfo='85;#' ows_owshiddenversion='1' ows_Created='2014-02-12 14:04:13' />
   <z:row ows_ID='86' ows_Attachments='0' ows_Campaign_id='25' ows_Stage='priority' ows_Score='1' ows_Override='0' ows_StartDate='2014-02-14 00:00:00' ows_Roi='0.00' ows_RoiPass='0' ows_HasPreanalysis='1' ows_Nicpl='0.00' ows_NicplPass='0' ows_Nic='0' ows__ModerationStatus='0' ows__Level='1' ows_UniqueId='86;#{933D4DCA-1CD9-498F-B1F7-3A3F2102545A}' ows_FSObjType='86;#0' ows_Created_x0020_Date='86;#2014-02-12 14:04:13' ows_FileLeafRef='86;#86_.000' ows_FileRef='86;#sites/rbs/DDM/Lists/prodoutcomecampaign/86_.000' ows_MetaInfo='86;#' ows_owshiddenversion='1' ows_Created='2014-02-12 14:04:13' />
   <z:row ows_ID='87' ows_Attachments='0' ows_Campaign_id='63' ows_Stage='priority' ows_Score='2' ows_Override='0' ows_StartDate='2014-03-03 00:00:00' ows_Roi='88.41' ows_RoiPass='1' ows_HasPreanalysis='1' ows_Nicpl='1.19' ows_NicplPass='0' ows_Nic='429,660' ows__ModerationStatus='0' ows__Level='1' ows_UniqueId='87;#{4AA306EE-87AD-40B6-8FA3-9164A04400F8}' ows_FSObjType='87;#0' ows_Created_x0020_Date='87;#2014-02-12 14:04:13' ows_FileLeafRef='87;#87_.000' ows_FileRef='87;#sites/rbs/DDM/Lists/prodoutcomecampaign/87_.000' ows_MetaInfo='87;#' ows_owshiddenversion='1' ows_Created='2014-02-12 14:04:13' />
   <z:row ows_ID='88' ows_Attachments='0' ows_Campaign_id='43' ows_Stage='priority' ows_Score='0' ows_Override='0' ows_StartDate='2014-02-04 00:00:00' ows_Roi='0.00' ows_RoiPass='0' ows_HasPreanalysis='0' ows_Nicpl='0.00' ows_NicplPass='0' ows_Nic='0' ows__ModerationStatus='0' ows__Level='1' ows_UniqueId='88;#{4FD8CF1D-56DA-46D5-8C5B-94C36DF96BA7}' ows_FSObjType='88;#0' ows_Created_x0020_Date='88;#2014-02-12 14:04:13' ows_FileLeafRef='88;#88_.000' ows_FileRef='88;#sites/rbs/DDM/Lists/prodoutcomecampaign/88_.000' ows_MetaInfo='88;#' ows_owshiddenversion='1' ows_Created='2014-02-12 14:04:13' />
</rs:data>
</listitems></GetListItemsResult></GetListItemsResponse></soap:Body></soap:Envelope>